{"aivis": [["2nd-December-1985", 8, 0, 8.4076]], "aivia": [["25th-Augus-2003", 129, 41, 8.4076]], "aiv": [["16th-November-2009", 49, 7, 7.30899], ["6th-October-2009", 70, 4, 7.30899], ["25th-June-1968", 44, 12, 7.30899]], "aivi": [["5th-December-1973", 46, 5, 7.71445], ["15th-December-1976", 28, 73, 7.71445]], "aiv5": [["30th-May-1997", 83, 8, 8.4076]], "aiv11": [["30th-May-1997", 83, 12, 8.4076]], "aiv671314": [["30th-May-1997", 83, 19, 8.4076]], "aiv12": [["30th-May-1997", 83, 57, 8.4076]], "aiv8": [["30th-May-1997", 83, 61, 8.4076]], "aiv1": [["30th-May-1997", 83, 64, 8.4076]], "aiv10": [["30th-May-1997", 85, 23, 8.4076]], "aiv9": [["30th-May-1997", 85, 48, 8.4076]], "aiv23": [["30th-May-1997", 84, 17, 8.4076]], "aivort": [["27th-Augus-1976", 1, 4, 8.4076]], "aivat": [["27th-May-1990", 11, 47, 8.4076]], "aivo": [["7th-February-1989", 26, 26, 8.4076]], "aivalogat": [["18th-Augus-1976", 3, 4, 8.4076]]}