{"ccharg": [["23rd-June-2009", 10, 7, 8.4076]], "cch": [["31st-Augus-1998", 52, 30, 7.71445], ["18th-Augus-1994", 29, 12, 7.71445]], "cchyderabad": [["18th-June-1997", 45, 40, 7.71445], ["21st-Augus-1997", 5, 29, 7.71445]], "cchair": [["11th-January-2010", 76, 7, 8.4076]], "cchf": [["7th-November-2018", 54, 1, 15.42891], ["7th-November-2018", 55, 0, 15.42891], ["13th-January-2010", 82, 18, 7.71445]], "ccheck": [["24th-September-1998", 59, 5, 16.8152], ["24th-September-1998", 59, 6, 16.8152]], "cchesion": [["10th-February-1990", 32, 6, 8.4076]], "cchd": [["4th-June-1999", 27, 18, 8.4076]], "cchievement": [["13th-June-1967", 44, 42, 8.4076]]}