{"dlak": [["1st-December-1985", 10, 14, 8.4076]], "dla": [["18th-October-2021", 14, 3, 23.37061], ["18th-October-2021", 14, 4, 23.37061], ["18th-October-2021", 14, 6, 23.37061], ["18th-October-2021", 14, 8, 23.37061], ["12th-June-2009", 75, 14, 5.84265], ["30th-June-1976", 9, 0, 5.84265], ["6th-October-2007", 8, 1, 11.6853], ["6th-October-2007", 8, 3, 11.6853], ["24th-May-1973", 3, 55, 5.84265], ["23rd-Augus-1976", 7, 0, 5.84265], ["11th-January-1999", 77, 22, 5.84265], ["7th-December-1985", 101, 16, 5.84265], ["4th-Augus-2006", 5, 0, 5.84265], ["3rd-Marc-1974", 2, 14, 5.84265], ["6th-June-2007", 8, 0, 5.84265], ["17th-January-2022", 20, 6, 11.6853], ["17th-January-2022", 21, 13, 11.6853], ["24th-Augus-1972", 26, 6, 5.84265]], "dlam": [["21st-Augus-1995", 95, 0, 8.4076]], "dlabi": [["5th-October-1986", 13, 24, 8.4076]], "dlalian": [["24th-April-2008", 42, 12, 8.4076]], "dlack": [["29th-Marc-2004", 121, 3, 8.4076]], "dladg": [["18th-April-1988", 18, 0, 8.4076]], "dlarejo": [["19th-February-1992", 79, 11, 8.4076]], "dlalanin": [["25th-June-1974", 18, 1, 8.4076]], "dlation": [["18th-December-1995", 39, 1, 8.4076]], "dlan": [["13th-June-2014", 93, 1, 8.4076]], "dlast": [["12th-April-1988", 37, 3, 8.4076]]}