{"ermeyya": [["23rd-January-1986", 20, 1, 8.4076]], "erman": [["10th-November-2008", 52, 13, 7.71445], ["9th-May-1968", 55, 8, 7.71445]], "ermin": [["19th-June-1962", 39, 13, 6.46169], ["13th-February-1957", 55, 15, 6.46169], ["4th-January-1950", 13, 24, 6.46169], ["29th-June-1966", 35, 8, 6.46169], ["22nd-April-1998", 32, 1, 6.46169], ["11th-Augus-1947", 16, 24, 6.46169], ["14th-June-1966", 38, 20, 6.46169]], "erment": [["17th-Augus-1964", 84, 27, 6.79816], ["7th-December-1962", 23, 7, 6.79816], ["13th-October-1950", 43, 11, 6.79816], ["11th-October-1950", 8, 17, 6.79816], ["6th-January-1949", 27, 25, 6.79816]], "ermal": [["18th-October-2005", 41, 7, 7.71445], ["5th-June-1998", 119, 60, 7.71445]], "erm": [["27th-Augus-2013", 12, 0, 6.46169], ["17th-December-2018", 43, 2, 6.46169], ["29th-June-1967", 8, 5, 6.46169], ["16th-December-1993", 45, 28, 6.46169], ["9th-June-1964", 55, 13, 6.46169], ["29th-June-1973", 11, 0, 6.46169], ["7th-June-1966", 65, 40, 6.46169]], "erminist": [["4th-April-1963", 35, 0, 7.30899], ["3rd-April-1963", 65, 15, 7.30899], ["30th-Marc-1964", 23, 12, 14.61798], ["30th-Marc-1964", 24, 22, 14.61798]], "ermna": [["7th-April-1997", 42, 9, 7.30899], ["31st-May-1994", 17, 13, 14.61798], ["31st-May-1994", 19, 68, 14.61798], ["1st-December-1967", 78, 2, 14.61798], ["1st-December-1967", 78, 31, 14.61798]], "erminalia": [["5th-October-1986", 58, 81, 8.4076]], "ermou": [["17th-December-1973", 17, 12, 8.4076]], "ermont": [["22nd-January-1995", 128, 7, 7.71445], ["19th-September-1989", 54, 26, 7.71445]], "ermpa": [["22nd-May-1997", 5, 25, 8.4076]], "ermarion": [["5th-June-1991", 103, 0, 8.4076]], "ermobi": [["11th-Augus-1973", 57, 5, 8.4076]], "ermmit": [["18th-June-1975", 119, 29, 8.4076]], "ermswhat": [["11th-December-1988", 5, 12, 8.4076]], "ermemb": [["1st-December-1967", 77, 8, 8.4076]], "ermma": [["4th-May-1976", 18, 20, 8.4076]], "ermmun": [["30th-December-1948", 47, 13, 8.4076]], "ermit": [["25th-November-1950", 49, 18, 8.4076]], "ermiss": [["8th-February-1956", 1, 7, 8.4076]]}