{"iolin": [["1st-December-1985", 62, 2, 8.4076]], "iol": [["1st-February-1987", 32, 54, 7.02131], ["5th-December-1973", 25, 22, 7.02131], ["20th-October-2003", 75, 34, 7.02131], ["22nd-Augus-1996", 142, 8, 7.02131]], "iola": [["11th-Marc-1966", 20, 7, 7.71445], ["24th-January-1969", 25, 23, 7.71445]], "iolat": [["27th-June-2020", 326, 0, 6.79816], ["26th-June-2021", 557, 1, 6.79816], ["9th-Augus-2007", 85, 1, 6.79816], ["25th-February-2014", 50, 11, 6.79816], ["30th-July-2004", 204, 0, 6.79816]], "iolo": [["27th-December-2021", 36, 3, 8.4076]], "iolidw": [["29th-November-1973", 15, 8, 8.4076]], "ioli": [["11th-May-1976", 39, 25, 8.4076]], "iolet": [["11th-June-1989", 141, 0, 8.4076]]}