{"obrien": [["30th-Marc-1963", 60, 11, 21.92697], ["30th-Marc-1963", 59, 18, 21.92697], ["30th-Marc-1963", 53, 26, 21.92697], ["20th-September-1972", 40, 58, 7.30899], ["2nd-September-1958", 73, 42, 7.30899]], "obro": [["6th-October-1985", 163, 0, 6.46169], ["2nd-Augus-2019", 46, 1, 6.46169], ["26th-November-1973", 53, 29, 6.46169], ["27th-December-2021", 39, 6, 6.46169], ["5th-December-1973", 45, 2, 6.46169], ["4th-December-1973", 34, 21, 6.46169], ["28th-November-1973", 46, 9, 6.46169]], "obrain": [["25th-June-1962", 12, 32, 7.71445], ["10th-June-1991", 62, 21, 7.71445]], "obradi": [["30th-November-1973", 2, 15, 8.4076]], "obr": [["15th-October-2005", 64, 0, 7.02131], ["29th-January-1975", 35, 28, 7.02131], ["24th-April-1957", 17, 7, 7.02131], ["20th-April-1994", 56, 7, 7.02131]], "obraj": [["7th-November-2022", 48, 0, 8.4076]], "obros": [["22nd-January-2013", 22, 0, 8.4076]], "obrad": [["5th-December-1973", 32, 8, 8.4076]], "obrom": [["29th-June-1987", 124, 0, 8.4076]], "obrah": [["6th-February-2017", 104, 2, 8.4076]], "obrini": [["29th-November-1973", 40, 15, 8.4076]], "obrod": [["28th-Marc-2022", 13, 11, 8.4076]], "obrdat": [["30th-June-1973", 18, 10, 8.4076]], "obri": [["12th-April-1988", 83, 0, 8.4076]], "obrerv": [["6th-May-1968", 37, 18, 8.4076]]}