{"ocil": [["7th-April-1994", 117, 7, 16.8152], ["7th-April-1994", 117, 99, 16.8152]], "ocin": [["7th-April-1994", 118, 93, 8.4076]], "ocial": [["22nd-February-1949", 24, 11, 7.71445], ["1st-September-1958", 2, 0, 7.71445]], "ociat": [["10th-July-1972", 36, 18, 8.4076]], "oci": [["21st-September-1985", 33, 0, 6.79816], ["7th-May-1991", 66, 17, 6.79816], ["17th-October-1985", 52, 0, 6.79816], ["27th-November-1973", 18, 20, 6.79816], ["8th-October-1989", 21, 14, 6.79816]], "ocip": [["3rd-May-2019", 53, 10, 8.4076]], "ociran": [["31st-October-1997", 30, 35, 8.4076]], "ocipur": [["27th-January-1999", 39, 9, 7.71445], ["4th-January-1999", 82, 61, 7.71445]], "ocieti": [["9th-December-2005", 27, 16, 8.4076]], "ocion": [["27th-Marc-1996", 66, 16, 8.4076]], "ocinion": [["2nd-December-1966", 61, 30, 8.4076]], "ocior": [["15th-June-1967", 40, 3, 8.4076]]}