{"ofsr": [["21st-Marc-2005", 44, 63, 8.4076]], "ofstapiss": [["27th-June-1973", 1, 3, 8.4076]], "ofsii": [["26th-February-2003", 69, 10, 8.4076]], "ofship": [["14th-Marc-2018", 30, 9, 8.4076]], "ofshal": [["13th-April-1963", 13, 24, 8.4076]], "ofstrength": [["2nd-April-1997", 30, 1, 8.4076]], "ofservic": [["1st-October-1985", 83, 23, 8.4076]], "ofslamabad": [["17th-Augus-2007", 8, 1, 8.4076]], "ofstacod": [["1st-April-2004", 79, 0, 8.4076]], "ofselfdetermin": [["19th-Augus-1954", 13, 41, 8.4076]], "ofsion": [["13th-November-2006", 21, 0, 8.4076]], "ofster": [["11th-Augus-2008", 22, 0, 8.4076]]}