{"otel": [["11th-December-1973", 25, 22, 6.79816], ["27th-November-1973", 16, 5, 6.79816], ["27th-June-1973", 75, 13, 6.79816], ["14th-September-1987", 75, 0, 6.79816], ["2nd-September-1976", 15, 83, 6.79816]], "otedsb": [["30th-November-1973", 35, 11, 8.4076]], "ote": [["5th-October-1986", 118, 1, 6.00971], ["31st-May-1994", 67, 10, 6.00971], ["1st-September-1976", 45, 0, 6.00971], ["7th-December-1973", 41, 3, 6.00971], ["26th-Augus-1976", 47, 0, 6.00971], ["5th-October-1985", 49, 3, 6.00971], ["28th-September-1950", 2, 20, 6.00971], ["30th-June-1973", 71, 1, 6.00971], ["2nd-Augus-1954", 8, 13, 6.00971], ["21st-December-1988", 17, 4, 6.00971], ["9th-Marc-2006", 20, 0, 18.02912], ["9th-Marc-2006", 21, 0, 18.02912]], "oteent": [["2nd-May-2006", 50, 0, 16.8152], ["2nd-May-2006", 50, 1, 16.8152]], "oteini": [["26th-November-1973", 13, 17, 8.4076]], "oter": [["27th-November-1973", 22, 1, 7.02131], ["16th-February-1986", 7, 6, 14.04261], ["16th-September-2004", 76, 0, 7.02131], ["11th-February-1992", 10, 3, 7.02131]], "otelul": [["24th-June-1976", 105, 0, 8.4076]], "otehr": [["17th-June-1989", 15, 2, 7.30899], ["12th-June-1996", 111, 7, 7.30899], ["23rd-Augus-1995", 40, 9, 7.30899]], "otest": [["16th-January-1950", 33, 17, 8.4076]], "oteti": [["1st-September-1976", 13, 4, 8.4076]], "otect": [["30th-May-1967", 78, 2, 8.4076]], "oteinim": [["29th-November-1973", 31, 13, 7.71445], ["7th-November-2018", 46, 4, 7.71445]], "otern": [["1st-December-1967", 78, 30, 8.4076]], "otersis": [["25th-June-1996", 58, 11, 8.4076]], "otesilqini": [["9th-July-1973", 29, 4, 8.4076]], "otestnummo": [["4th-December-1973", 38, 2, 8.4076]]}